mir/sqlite3m/__init__.py
mir.sqlite3m-1.0.0.dist-info/DESCRIPTION.rst
mir.sqlite3m-1.0.0.dist-info/METADATA
mir.sqlite3m-1.0.0.dist-info/RECORD
mir.sqlite3m-1.0.0.dist-info/WHEEL
mir.sqlite3m-1.0.0.dist-info/metadata.json
mir.sqlite3m-1.0.0.dist-info/top_level.txt
